popstock/PopulationOmegaGW.py
popstock/__init__.py
popstock/_version.py
popstock/constants.py
popstock/util.py
popstock-0.2.1.data/scripts/population_O3
popstock-0.2.1.data/scripts/population_O3_fixed_samples
popstock-0.2.1.data/scripts/population_O3_new_draws
popstock-0.2.1.dist-info/licenses/LICENSE
popstock-0.2.1.dist-info/METADATA
popstock-0.2.1.dist-info/WHEEL
popstock-0.2.1.dist-info/top_level.txt
popstock-0.2.1.dist-info/RECORD
