Metadata-Version: 2.4
Name: popstock
Version: 0.2.1
Summary: A lightweight package for fast evaluation of the stochastic GW energy density Omega_GW emitted by a population of binary black holes and/or neutron stars.
Home-page: https://git.ligo.org/arianna.renzini/popstock
Author: Arianna Renzini, Jacob Golomb
Author-email: aria.renzini@gmail.com
License: MIT
Classifier: Programming Language :: Python :: 3.9
Classifier: Programming Language :: Python :: 3.10
Classifier: Programming Language :: Python :: 3.11
Classifier: License :: OSI Approved :: MIT License
Classifier: Operating System :: OS Independent
Requires-Python: >=3.9
License-File: LICENSE
Requires-Dist: numpy
Requires-Dist: scipy>=1.8.0
Requires-Dist: bilby>=1.4
Requires-Dist: gwpy>=3.0.4
Requires-Dist: astropy>=5.2
Requires-Dist: gwpopulation
Requires-Dist: lalsuite>=7.3
Provides-Extra: dev
Requires-Dist: pytest; extra == "dev"
Dynamic: author
Dynamic: author-email
Dynamic: classifier
Dynamic: home-page
Dynamic: license
Dynamic: license-file
Dynamic: provides-extra
Dynamic: requires-dist
Dynamic: requires-python
Dynamic: summary
